pytest_blockage.py
pytest_blockage-0.2.4.dist-info/LICENSE
pytest_blockage-0.2.4.dist-info/METADATA
pytest_blockage-0.2.4.dist-info/WHEEL
pytest_blockage-0.2.4.dist-info/entry_points.txt
pytest_blockage-0.2.4.dist-info/top_level.txt
pytest_blockage-0.2.4.dist-info/RECORD
