Metadata-Version: 2.1
Name: pytest-blockage
Version: 0.2.4
Summary: Disable network requests during a test run.
Home-page: https://github.com/rob-b/pytest-blockage
License: BSD
Platform: UNKNOWN
Classifier: Intended Audience :: Developers
Classifier: Natural Language :: English
Classifier: Operating System :: OS Independent
License-File: LICENSE
Requires-Dist: pytest
